[{"Palette":{"modes":{"Mode 1":{"gray":{"0":{"$scopes":["ALL_SCOPES"],"$type":"color","$value":"#ffffff"},"50":{"$scopes":["ALL_SCOPES"],"$type":"color","$value":"#f8fafc"},"100":{"$scopes":["ALL_SCOPES"],"$type":"color","$value":"#f1f5f9"},"200":{"$scopes":["ALL_SCOPES"],"$type":"color","$value":"#e2e8f0"},"300":{"$scopes":["ALL_SCOPES"],"$type":"color","$value":"#cbd5e1"},"400":{"$scopes":["ALL_SCOPES"],"$type":"color","$value":"#94a3b8"},"500":{"$scopes":["ALL_SCOPES"],"$type":"color","$value":"#64748b"},"600":{"$scopes":["ALL_SCOPES"],"$type":"color","$value":"#475569"},"700":{"$scopes":["ALL_SCOPES"],"$type":"color","$value":"#334155"},"800":{"$scopes":["ALL_SCOPES"],"$type":"color","$value":"#1e293b"},"900":{"$scopes":["ALL_SCOPES"],"$type":"color","$value":"#0f172a"}},"red":{"1":{"$scopes":["ALL_SCOPES"],"$type":"color","$value":"#fffafa"},"100":{"$scopes":["ALL_SCOPES"],"$type":"color","$value":"#fed5d5"},"200":{"$scopes":["ALL_SCOPES"],"$type":"color","$value":"#ffb5b5"},"300":{"$scopes":["ALL_SCOPES"],"$type":"color","$value":"#ff8c8c"},"400":{"$scopes":["ALL_SCOPES"],"$type":"color","$value":"#ff6363"},"500":{"$scopes":["ALL_SCOPES"],"$type":"color","$value":"#ff4242"},"600":{"$scopes":["ALL_SCOPES"],"$type":"color","$value":"#e52222"},"700":{"$scopes":["ALL_SCOPES"],"$type":"color","$value":"#b00c0c"},"800":{"$scopes":["ALL_SCOPES"],"$type":"color","$value":"#730303"},"900":{"$scopes":["ALL_SCOPES"],"$type":"color","$value":"#3b0101"}},"orange":{"1":{"$scopes":["ALL_SCOPES"],"$type":"color","$value":"#fff8f5"},"100":{"$scopes":["ALL_SCOPES"],"$type":"color","$value":"#fee2d7"},"200":{"$scopes":["ALL_SCOPES"],"$type":"color","$value":"#ffc8b2"},"300":{"$scopes":["ALL_SCOPES"],"$type":"color","$value":"#ffab8a"},"400":{"$scopes":["ALL_SCOPES"],"$type":"color","$value":"#ff8e61"},"500":{"$scopes":["ALL_SCOPES"],"$type":"color","$value":"#ff7842"},"600":{"$scopes":["ALL_SCOPES"],"$type":"color","$value":"#f15a22"},"700":{"$scopes":["ALL_SCOPES"],"$type":"color","$value":"#b03b0c"},"800":{"$scopes":["ALL_SCOPES"],"$type":"color","$value":"#722303"},"900":{"$scopes":["ALL_SCOPES"],"$type":"color","$value":"#3c1201"}},"yellow":{"1":{"$scopes":["ALL_SCOPES"],"$type":"color","$value":"#fffcf0"},"100":{"$scopes":["ALL_SCOPES"],"$type":"color","$value":"#fef8d7"},"200":{"$scopes":["ALL_SCOPES"],"$type":"color","$value":"#fff2b2"},"300":{"$scopes":["ALL_SCOPES"],"$type":"color","$value":"#ffeb8a"},"400":{"$scopes":["ALL_SCOPES"],"$type":"color","$value":"#ffe561"},"500":{"$scopes":["ALL_SCOPES"],"$type":"color","$value":"#ffde38"},"600":{"$scopes":["ALL_SCOPES"],"$type":"color","$value":"#d4b100"},"700":{"$scopes":["ALL_SCOPES"],"$type":"color","$value":"#a78d0c"},"800":{"$scopes":["ALL_SCOPES"],"$type":"color","$value":"#685703"},"900":{"$scopes":["ALL_SCOPES"],"$type":"color","$value":"#3c3201"}},"green":{"1":{"$scopes":["ALL_SCOPES"],"$type":"color","$value":"#f3fef4"},"100":{"$scopes":["ALL_SCOPES"],"$type":"color","$value":"#d9f9db"},"200":{"$scopes":["ALL_SCOPES"],"$type":"color","$value":"#bcf5c1"},"300":{"$scopes":["ALL_SCOPES"],"$type":"color","$value":"#99f2a1"},"400":{"$scopes":["ALL_SCOPES"],"$type":"color","$value":"#80e788"},"500":{"$scopes":["ALL_SCOPES"],"$type":"color","$value":"#4fe45b"},"600":{"$scopes":["ALL_SCOPES"],"$type":"color","$value":"#15bf23"},"700":{"$scopes":["ALL_SCOPES"],"$type":"color","$value":"#12a11e"},"800":{"$scopes":["ALL_SCOPES"],"$type":"color","$value":"#0b6012"},"900":{"$scopes":["ALL_SCOPES"],"$type":"color","$value":"#013c06"}},"skyblue":{"1":{"$scopes":["ALL_SCOPES"],"$type":"color","$value":"#f0faff"},"100":{"$scopes":["ALL_SCOPES"],"$type":"color","$value":"#d7f2fe"},"200":{"$scopes":["ALL_SCOPES"],"$type":"color","$value":"#b2e7ff"},"300":{"$scopes":["ALL_SCOPES"],"$type":"color","$value":"#8ad9ff"},"400":{"$scopes":["ALL_SCOPES"],"$type":"color","$value":"#61ccff"},"500":{"$scopes":["ALL_SCOPES"],"$type":"color","$value":"#38bfff"},"600":{"$scopes":["ALL_SCOPES"],"$type":"color","$value":"#0092d6"},"700":{"$scopes":["ALL_SCOPES"],"$type":"color","$value":"#0c76a7"},"800":{"$scopes":["ALL_SCOPES"],"$type":"color","$value":"#034868"},"900":{"$scopes":["ALL_SCOPES"],"$type":"color","$value":"#01293c"}},"blue":{"1":{"$scopes":["ALL_SCOPES"],"$type":"color","$value":"#f0f7ff"},"50":{"$scopes":["ALL_SCOPES"],"$type":"color","$value":"#e6f2fe"},"100":{"$scopes":["ALL_SCOPES"],"$type":"color","$value":"#d7eafe"},"200":{"$scopes":["ALL_SCOPES"],"$type":"color","$value":"#b2d7ff"},"300":{"$scopes":["ALL_SCOPES"],"$type":"color","$value":"#8ac2ff"},"400":{"$scopes":["ALL_SCOPES"],"$type":"color","$value":"#61adff"},"500":{"$scopes":["ALL_SCOPES"],"$type":"color","$value":"#3898ff"},"600":{"$scopes":["ALL_SCOPES"],"$type":"color","$value":"#0b68cb"},"700":{"$scopes":["ALL_SCOPES"],"$type":"color","$value":"#004c9d"},"800":{"$scopes":["ALL_SCOPES"],"$type":"color","$value":"#033468"},"900":{"$scopes":["ALL_SCOPES"],"$type":"color","$value":"#011e3c"}},"dimmed":{"5":{"$scopes":["ALL_SCOPES"],"$type":"color","$value":"rgba(23, 23, 25, 5)"},"12":{"$scopes":["ALL_SCOPES"],"$type":"color","$value":"rgba(23, 23, 25, 12)"},"65":{"$scopes":["ALL_SCOPES"],"$type":"color","$value":"rgba(23, 23, 25, 65)"}}}}}},{"semantic":{"modes":{"Mode 1":{"Primary":{"normal":{"$scopes":["ALL_SCOPES"],"$type":"color","$libraryName":"","$collectionName":"Palette","$value":"{blue.600}"},"strong":{"$scopes":["ALL_SCOPES"],"$type":"color","$libraryName":"","$collectionName":"Palette","$value":"{blue.700}"},"heavy":{"$scopes":["ALL_SCOPES"],"$type":"color","$libraryName":"","$collectionName":"Palette","$value":"{blue.800}"}},"Secondary":{"normal":{"$scopes":["ALL_SCOPES"],"$type":"color","$libraryName":"","$collectionName":"Palette","$value":"{skyblue.600}"},"storng":{"$scopes":["ALL_SCOPES"],"$type":"color","$libraryName":"","$collectionName":"Palette","$value":"{skyblue.700}"},"heavy":{"$scopes":["ALL_SCOPES"],"$type":"color","$libraryName":"","$collectionName":"Palette","$value":"{skyblue.800}"}},"Accent":{"normal":{"$scopes":["ALL_SCOPES"],"$type":"color","$libraryName":"","$collectionName":"Palette","$value":"{orange.500}"}},"Common":{"white":{"$scopes":["ALL_SCOPES"],"$type":"color","$libraryName":"","$collectionName":"Palette","$value":"{gray.0}"},"black":{"$scopes":["ALL_SCOPES"],"$type":"color","$libraryName":"","$collectionName":"Palette","$value":"{gray.900}"}},"Label":{"normal":{"$scopes":["ALL_SCOPES"],"$type":"color","$libraryName":"","$collectionName":"Palette","$value":"{gray.800}"},"strong":{"$scopes":["ALL_SCOPES"],"$type":"color","$libraryName":"","$collectionName":"Palette","$value":"{gray.900}"},"alternative":{"$scopes":["ALL_SCOPES"],"$type":"color","$libraryName":"","$collectionName":"Palette","$value":"{gray.500}"},"assistive":{"$scopes":["ALL_SCOPES"],"$type":"color","$libraryName":"","$collectionName":"Palette","$value":"{gray.400}"},"disable":{"$scopes":["ALL_SCOPES"],"$type":"color","$libraryName":"","$collectionName":"Palette","$value":"{gray.500}"}},"Background":{"weak":{"$scopes":["ALL_SCOPES"],"$type":"color","$libraryName":"","$collectionName":"Palette","$value":"{gray.50}"},"normal":{"$scopes":["ALL_SCOPES"],"$type":"color","$libraryName":"","$collectionName":"Palette","$value":"{gray.100}"},"strong":{"$scopes":["ALL_SCOPES"],"$type":"color","$libraryName":"","$collectionName":"Palette","$value":"{gray.200}"},"heavy":{"$scopes":["ALL_SCOPES"],"$type":"color","$libraryName":"","$collectionName":"Palette","$value":"{gray.300}"}},"Line":{"weak":{"$scopes":["ALL_SCOPES"],"$type":"color","$libraryName":"","$collectionName":"Palette","$value":"{gray.200}"},"normal":{"$scopes":["ALL_SCOPES"],"$type":"color","$libraryName":"","$collectionName":"Palette","$value":"{gray.300}"},"strong":{"$scopes":["ALL_SCOPES"],"$type":"color","$libraryName":"","$collectionName":"Palette","$value":"{gray.400}"}},"Icon":{"white":{"$scopes":["ALL_SCOPES"],"$type":"color","$libraryName":"","$collectionName":"Palette","$value":"{gray.0}"},"normal":{"$scopes":["ALL_SCOPES"],"$type":"color","$libraryName":"","$collectionName":"Palette","$value":"{gray.300}"},"strong":{"$scopes":["ALL_SCOPES"],"$type":"color","$libraryName":"","$collectionName":"Palette","$value":"{gray.500}"},"heavy":{"$scopes":["ALL_SCOPES"],"$type":"color","$libraryName":"","$collectionName":"Palette","$value":"{gray.700}"}},"Status":{"success":{"$scopes":["ALL_SCOPES"],"$type":"color","$libraryName":"","$collectionName":"Palette","$value":"{green.600}"},"caution":{"$scopes":["ALL_SCOPES"],"$type":"color","$libraryName":"","$collectionName":"Palette","$value":"{yellow.500}"},"error":{"$scopes":["ALL_SCOPES"],"$type":"color","$libraryName":"","$collectionName":"Palette","$value":"{red.500}"}}}}}}]